jlab_ext_example/__init__.py
jlab_ext_example/_version.py
jlab_ext_example/handlers.py
jlab_ext_example/labextension/build_log.json
jlab_ext_example/labextension/package.json
jlab_ext_example/labextension/static/lib_index_js.f6cc92d046520f006b0e.js
jlab_ext_example/labextension/static/lib_index_js.f6cc92d046520f006b0e.js.map
jlab_ext_example/labextension/static/remoteEntry.bda60c5cf92a55bea4a0.js
jlab_ext_example/labextension/static/remoteEntry.bda60c5cf92a55bea4a0.js.map
jlab_ext_example/labextension/static/style.js
jlab_ext_example/labextension/static/style_index_js.15428bfc2281a837da0f.js
jlab_ext_example/labextension/static/style_index_js.15428bfc2281a837da0f.js.map
jlab_ext_example/labextension/static/vendors-node_modules_css-loader_dist_runtime_api_js-node_modules_css-loader_dist_runtime_cssW-72eba1.93d94b6e56b10209c3ec.js
jlab_ext_example/labextension/static/vendors-node_modules_css-loader_dist_runtime_api_js-node_modules_css-loader_dist_runtime_cssW-72eba1.93d94b6e56b10209c3ec.js.map
jlab_ext_example/public/index.html
jlab_ext_example-0.1.0.data/data/etc/jupyter/jupyter_notebook_config.d/jlab_ext_example.json
jlab_ext_example-0.1.0.data/data/etc/jupyter/jupyter_server_config.d/jlab_ext_example.json
jlab_ext_example-0.1.0.data/data/share/jupyter/labextensions/@jupyterlab-examples/server-extension/build_log.json
jlab_ext_example-0.1.0.data/data/share/jupyter/labextensions/@jupyterlab-examples/server-extension/install.json
jlab_ext_example-0.1.0.data/data/share/jupyter/labextensions/@jupyterlab-examples/server-extension/package.json
jlab_ext_example-0.1.0.data/data/share/jupyter/labextensions/@jupyterlab-examples/server-extension/static/lib_index_js.f6cc92d046520f006b0e.js
jlab_ext_example-0.1.0.data/data/share/jupyter/labextensions/@jupyterlab-examples/server-extension/static/lib_index_js.f6cc92d046520f006b0e.js.map
jlab_ext_example-0.1.0.data/data/share/jupyter/labextensions/@jupyterlab-examples/server-extension/static/remoteEntry.bda60c5cf92a55bea4a0.js
jlab_ext_example-0.1.0.dist-info/LICENSE
jlab_ext_example-0.1.0.dist-info/METADATA
jlab_ext_example-0.1.0.dist-info/WHEEL
jlab_ext_example-0.1.0.dist-info/top_level.txt
jlab_ext_example-0.1.0.dist-info/RECORD
